todo_merger/__init__.py
todo_merger/_auth.py
todo_merger/_cache.py
todo_merger/_config.py
todo_merger/_github.py
todo_merger/_gitlab.py
todo_merger/_helpers.py
todo_merger/_issues.py
todo_merger/_msplanner.py
todo_merger/_private_tasks.py
todo_merger/_types.py
todo_merger/_views.py
todo_merger/main.py
todo_merger/static/css/pico.min.css
todo_merger/static/fontawesome/fontawesome-all.min.css
todo_merger/static/img/android-chrome-192x192.png
todo_merger/static/img/android-chrome-512x512.png
todo_merger/static/img/apple-touch-icon.png
todo_merger/static/img/browserconfig.xml
todo_merger/static/img/favicon-16x16.png
todo_merger/static/img/favicon-32x32.png
todo_merger/static/img/favicon.ico
todo_merger/static/img/logo.svg
todo_merger/static/img/mstile-150x150.png
todo_merger/static/img/safari-pinned-tab.svg
todo_merger/static/img/site.webmanifest
todo_merger/static/sass/custom.scss
todo_merger/static/webfonts/fa-brands-400.ttf
todo_merger/static/webfonts/fa-brands-400.woff2
todo_merger/static/webfonts/fa-regular-400.ttf
todo_merger/static/webfonts/fa-regular-400.woff2
todo_merger/static/webfonts/fa-solid-900.ttf
todo_merger/static/webfonts/fa-solid-900.woff2
todo_merger/static/webfonts/fa-v4compatibility.ttf
todo_merger/static/webfonts/fa-v4compatibility.woff2
todo_merger/templates/base.html
todo_merger/templates/error.html
todo_merger/templates/flash.html
todo_merger/templates/index.html
todo_merger/templates/new.html
todo_merger-1.2.3.dist-info/METADATA
todo_merger-1.2.3.dist-info/WHEEL
todo_merger-1.2.3.dist-info/entry_points.txt
todo_merger-1.2.3.dist-info/licenses/LICENSE.txt
todo_merger-1.2.3.dist-info/RECORD
