Metadata-Version: 2.4
Name: todo-merger
Version: 1.2.3
Summary: Provide an overview of your assigned issues on GitLab, GitLab and Microsoft Planner
License: GPL-3.0-only
License-File: LICENSE.txt
Author: Max Mehl
Author-email: mail@mehl.mx
Requires-Python: >=3.10,<4.0
Classifier: License :: OSI Approved :: GNU General Public License v3 (GPLv3)
Classifier: Programming Language :: Python :: 3
Classifier: Programming Language :: Python :: 3.10
Classifier: Programming Language :: Python :: 3.11
Classifier: Programming Language :: Python :: 3.12
Classifier: Programming Language :: Python :: 3.13
Classifier: Programming Language :: Python :: 3.14
Requires-Dist: flask (>=3.1.2,<4.0.0)
Requires-Dist: libsass (>=0.23.0,<0.24.0)
Requires-Dist: platformdirs (>=4.5.0,<5.0.0)
Requires-Dist: pygithub (>=2.8.1,<3.0.0)
Requires-Dist: python-daemon (>=3.1.2,<4.0.0)
Requires-Dist: python-dateutil (>=2.9.0.post0,<3.0.0)
Requires-Dist: python-gitlab (>=7.0.0,<8.0.0)
Requires-Dist: setuptools (>=80.9.0,<81.0.0)
Requires-Dist: toml (>=0.10.2,<0.11.0)
Project-URL: Repository, https://github.com/mxmehl/todo-merger
